{"schema": ["lcsc", "mfr", "joints", "manufacturer", "description", "datasheet", "price", "images", "url", "attributes"], "components": [["C727527", "SUD50N04-8M8P-4GE3", 3, "Vishay Intertech", "TO-252-3 Pre-ordered transistors RoHS", "https://datasheet.lcsc.com/szlcsc/2011031008_Vishay-Intertech-SUD50N04-8M8P-4GE3_C727527.pdf", [{"qFrom": 1, "qTo": 9, "price": 0.931818182}, {"qFrom": 10, "qTo": 29, "price": 0.698484848}, {"qFrom": 30, "qTo": 99, "price": 0.656060606}, {"qFrom": 100, "qTo": 499, "price": 0.612121212}, {"qFrom": 500, "qTo": 999, "price": 0.593939394}, {"qFrom": 1000, "qTo": null, "price": 0.584848485}], {"96x96": "https://assets.lcsc.com/images/szlcsc/96x96/C727527_front.jpg", "224x224": "https://assets.lcsc.com/images/szlcsc/224x224/C727527_front.jpg", "900x900": "https://assets.lcsc.com/images/szlcsc/900x900/C727527_front.jpg", "sort": 1}, "https://lcsc.com/product-detail/Pre-ordered-transistors_Vishay-Intertech-SUD50N04-8M8P-4GE3_C727527.html", {"Basic/Extended": {"format": "${default}", "primary": "default", "values": {"default": ["Extended", "string"]}}, "Package": {"format": "${default}", "primary": "default", "values": {"default": ["TO-252-2L", "string"]}}, "Status": {"format": "${default}", "primary": "default", "values": {"default": ["Active", "string"]}}}], ["C538807", "SAK-TC275T-64F200W DC", 176, "Infineon Technologies", "PG-LQFP-176 Pre-ordered transistors RoHS", "", [{"qFrom": 1, "qTo": 9, "price": 41.575757576}, {"qFrom": 10, "qTo": 29, "price": 41.575757576}, {"qFrom": 30, "qTo": 199, "price": 41.575757576}, {"qFrom": 200, "qTo": 499, "price": 16.089393939}, {"qFrom": 500, "qTo": 999, "price": 15.524242424}, {"qFrom": 1000, "qTo": null, "price": 15.245454545}], null, "https://lcsc.com/product-detail/Pre-ordered-transistors_Infineon-Technologies-SAK-TC275T-64F200W-DC_C538807.html", {"Basic/Extended": {"format": "${default}", "primary": "default", "values": {"default": ["Extended", "string"]}}, "Package": {"format": "${default}", "primary": "default", "values": {"default": ["QFP-176_EP_24.0x24.0x0.5P", "string"]}}, "Status": {"format": "${default}", "primary": "default", "values": {"default": ["Active", "string"]}}}], ["C604520", "NVATS5A114PLZT4G", 3, "ON Semiconductor", "TO-252-3 Pre-ordered transistors RoHS", "", [{"qFrom": 1, "qTo": 9, "price": 2.413636364}, {"qFrom": 10, "qTo": 29, "price": 2.413636364}, {"qFrom": 30, "qTo": 199, "price": 2.413636364}, {"qFrom": 200, "qTo": 499, "price": 0.934848485}, {"qFrom": 500, "qTo": 999, "price": 0.901515152}, {"qFrom": 1000, "qTo": null, "price": 0.886363636}], null, "https://lcsc.com/product-detail/Pre-ordered-transistors_ON-Semiconductor-NVATS5A114PLZT4G_C604520.html", {"Basic/Extended": {"format": "${default}", "primary": "default", "values": {"default": ["Extended", "string"]}}, "Package": {"format": "${default}", "primary": "default", "values": {"default": ["TO-252-3", "string"]}}, "Status": {"format": "${default}", "primary": "default", "values": {"default": ["Active", "string"]}}}], ["C909754", "MMBT3904", 3, "GOODWORK", "SOT-23 Pre-ordered transistors RoHS", "", [{"qFrom": 1, "qTo": 9, "price": 0.013090909}, {"qFrom": 10, "qTo": 29, "price": 0.013090909}, {"qFrom": 30, "qTo": 199, "price": 0.013090909}, {"qFrom": 200, "qTo": 499, "price": 0.005060606}, {"qFrom": 500, "qTo": 999, "price": 0.004893939}, {"qFrom": 1000, "qTo": null, "price": 0.00480303}], null, "https://lcsc.com/product-detail/Transistors-NPN-PNP_GOODWORK-MMBT3904_C909754.html", {"Transistor Type": {"format": "${default}", "primary": "default", "values": {"default": ["-", "string"]}}, "Current - Collector (Ic) (Max)": {"format": "${Ic}", "default": "Ic", "values": {"Ic": ["NaN", "current"]}}, "Voltage - Collector Emitter Breakdown (Max)": {"format": "${voltage}", "primary": "voltage", "values": {"voltage": ["NaN", "voltage"]}}, "Power": {"format": "${power}", "default": "power", "values": {"power": ["NaN", "power"]}}, "Basic/Extended": {"format": "${default}", "primary": "default", "values": {"default": ["Extended", "string"]}}, "Package": {"format": "${default}", "primary": "default", "values": {"default": ["SOT-23-3", "string"]}}, "Status": {"format": "${default}", "primary": "default", "values": {"default": ["Active", "string"]}}}], ["C604536", "NVD5C454NT4G", 3, "ON Semiconductor", "TO-252-3 Pre-ordered transistors RoHS", "", [{"qFrom": 1, "qTo": 9, "price": 0.954545455}, {"qFrom": 10, "qTo": 29, "price": 0.954545455}, {"qFrom": 30, "qTo": 199, "price": 0.954545455}, {"qFrom": 200, "qTo": 499, "price": 0.36969697}, {"qFrom": 500, "qTo": 999, "price": 0.357575758}, {"qFrom": 1000, "qTo": null, "price": 0.35}], null, "https://lcsc.com/product-detail/Pre-ordered-transistors_ON-Semiconductor-NVD5C454NT4G_C604536.html", {"Basic/Extended": {"format": "${default}", "primary": "default", "values": {"default": ["Extended", "string"]}}, "Package": {"format": "${default}", "primary": "default", "values": {"default": ["TO-252-3", "string"]}}, "Status": {"format": "${default}", "primary": "default", "values": {"default": ["Active", "string"]}}}], ["C533072", "2EDL8014G", 8, "Infineon Technologies", "PG-VDSON-8 Pre-ordered transistors RoHS", "", [{"qFrom": 1, "qTo": 9, "price": 2.356060606}, {"qFrom": 10, "qTo": 29, "price": 2.356060606}, {"qFrom": 30, "qTo": 199, "price": 2.356060606}, {"qFrom": 200, "qTo": 499, "price": 0.912121212}, {"qFrom": 500, "qTo": 999, "price": 0.88030303}, {"qFrom": 1000, "qTo": null, "price": 0.865151515}], null, "https://lcsc.com/product-detail/Pre-ordered-transistors_Infineon-Technologies-2EDL8014G_C533072.html", {"Basic/Extended": {"format": "${default}", "primary": "default", "values": {"default": ["Extended", "string"]}}, "Package": {"format": "${default}", "primary": "default", "values": {"default": ["PG-VDSON-8", "string"]}}, "Status": {"format": "${default}", "primary": "default", "values": {"default": ["Active", "string"]}}}], ["C602887", "BT134W-600,135", 4, "WeEn Semiconductors", "SOT223 Pre-ordered transistors RoHS", "", [{"qFrom": 1, "qTo": 9, "price": 0.439848485}, {"qFrom": 10, "qTo": 29, "price": 0.439848485}, {"qFrom": 30, "qTo": 199, "price": 0.439848485}, {"qFrom": 200, "qTo": 499, "price": 0.170151515}, {"qFrom": 500, "qTo": 999, "price": 0.164227273}, {"qFrom": 1000, "qTo": null, "price": 0.161272727}], null, "https://lcsc.com/product-detail/Pre-ordered-transistors_WeEn-Semiconductors-BT134W-600-135_C602887.html", {"Basic/Extended": {"format": "${default}", "primary": "default", "values": {"default": ["Extended", "string"]}}, "Package": {"format": "${default}", "primary": "default", "values": {"default": ["SOT-223", "string"]}}, "Status": {"format": "${default}", "primary": "default", "values": {"default": ["Active", "string"]}}}], ["C727622", "SI4214DDY-T1-E3", 8, "Vishay Intertech", "SO-8 Pre-ordered transistors RoHS", "", [{"qFrom": 1, "qTo": 9, "price": 1.628787879}, {"qFrom": 10, "qTo": 29, "price": 1.628787879}, {"qFrom": 30, "qTo": 199, "price": 1.628787879}, {"qFrom": 200, "qTo": 499, "price": 0.63030303}, {"qFrom": 500, "qTo": 999, "price": 0.609090909}, {"qFrom": 1000, "qTo": null, "price": 0.596969697}], null, "https://lcsc.com/product-detail/Pre-ordered-transistors_Vishay-Intertech-SI4214DDY-T1-E3_C727622.html", {"Basic/Extended": {"format": "${default}", "primary": "default", "values": {"default": ["Extended", "string"]}}, "Package": {"format": "${default}", "primary": "default", "values": {"default": ["SO-8", "string"]}}, "Status": {"format": "${default}", "primary": "default", "values": {"default": ["Active", "string"]}}}], ["C780128", "RCLAMP0544T.TCT", 9, "SEMTECH", "SMD Pre-ordered transistors RoHS", "", [{"qFrom": 1, "qTo": 9, "price": 1.833333333}, {"qFrom": 10, "qTo": 29, "price": 1.833333333}, {"qFrom": 30, "qTo": 199, "price": 1.833333333}, {"qFrom": 200, "qTo": 499, "price": 0.710606061}, {"qFrom": 500, "qTo": 999, "price": 0.684848485}, {"qFrom": 1000, "qTo": null, "price": 0.672727273}], null, "https://lcsc.com/product-detail/Pre-ordered-transistors_SEMTECH-RCLAMP0544T-TCT_C780128.html", {"Basic/Extended": {"format": "${default}", "primary": "default", "values": {"default": ["Extended", "string"]}}, "Package": {"format": "${default}", "primary": "default", "values": {"default": ["SMD", "string"]}}, "Status": {"format": "${default}", "primary": "default", "values": {"default": ["Active", "string"]}}}], ["C538819", "TC297TA128F300NBCKXUMA1", 292, "Infineon Technologies", "PG-LFBGA-292-6 Pre-ordered transistors RoHS", "", [{"qFrom": 1, "qTo": 29, "price": 49.45530303}, {"qFrom": 30, "qTo": null, "price": 48.676515152}], null, "https://lcsc.com/product-detail/Pre-ordered-transistors_Infineon-Technologies-TC297TA128F300NBCKXUMA1_C538819.html", {"Basic/Extended": {"format": "${default}", "primary": "default", "values": {"default": ["Extended", "string"]}}, "Package": {"format": "${default}", "primary": "default", "values": {"default": ["LF-BGA-292-6", "string"]}}, "Status": {"format": "${default}", "primary": "default", "values": {"default": ["Active", "string"]}}}], ["C604301", "NRVTS560EMFST1G", 5, "ON Semiconductor", "8-PowerTDFN Pre-ordered transistors RoHS", "", [{"qFrom": 1, "qTo": 9, "price": 0.306060606}, {"qFrom": 10, "qTo": 29, "price": 0.227272727}, {"qFrom": 30, "qTo": 99, "price": 0.212121212}, {"qFrom": 100, "qTo": 499, "price": 0.198484848}, {"qFrom": 500, "qTo": 999, "price": 0.192424242}, {"qFrom": 1000, "qTo": null, "price": 0.187878788}], null, "https://lcsc.com/product-detail/Pre-ordered-transistors_ON-Semiconductor-NRVTS560EMFST1G_C604301.html", {"Basic/Extended": {"format": "${default}", "primary": "default", "values": {"default": ["Extended", "string"]}}, "Package": {"format": "${default}", "primary": "default", "values": {"default": ["8-PowerTDFN", "string"]}}, "Status": {"format": "${default}", "primary": "default", "values": {"default": ["Active", "string"]}}}], ["C603959", "NCV5500DT33RKG", 5, "ON Semiconductor", "SOT-23-5 Pre-ordered transistors RoHS", "", [{"qFrom": 1, "qTo": 9, "price": 0.890909091}, {"qFrom": 10, "qTo": 29, "price": 0.890909091}, {"qFrom": 30, "qTo": 199, "price": 0.890909091}, {"qFrom": 200, "qTo": 499, "price": 0.345454545}, {"qFrom": 500, "qTo": 999, "price": 0.333333333}, {"qFrom": 1000, "qTo": null, "price": 0.327272727}], null, "https://lcsc.com/product-detail/Pre-ordered-transistors_ON-Semiconductor-NCV5500DT33RKG_C603959.html", {"Basic/Extended": {"format": "${default}", "primary": "default", "values": {"default": ["Extended", "string"]}}, "Package": {"format": "${default}", "primary": "default", "values": {"default": ["SOT-23-5", "string"]}}, "Status": {"format": "${default}", "primary": "default", "values": {"default": ["Active", "string"]}}}], ["C606163", "RHRG1560CC-F085", 3, "ON Semiconductor", "TO-247 Pre-ordered transistors RoHS", "", [{"qFrom": 1, "qTo": 9, "price": 2.812121212}, {"qFrom": 10, "qTo": 29, "price": 2.812121212}, {"qFrom": 30, "qTo": 199, "price": 2.812121212}, {"qFrom": 200, "qTo": 499, "price": 1.087878788}, {"qFrom": 500, "qTo": 999, "price": 1.05}, {"qFrom": 1000, "qTo": null, "price": 1.031818182}], null, "https://lcsc.com/product-detail/Pre-ordered-transistors_ON-Semiconductor-RHRG1560CC-F085_C606163.html", {"Basic/Extended": {"format": "${default}", "primary": "default", "values": {"default": ["Extended", "string"]}}, "Package": {"format": "${default}", "primary": "default", "values": {"default": ["TO-247-3", "string"]}}, "Status": {"format": "${default}", "primary": "default", "values": {"default": ["Active", "string"]}}}], ["C606164", "RURG3060CC-F085", 3, "ON Semiconductor", "TO-247-3 Pre-ordered transistors RoHS", "", [{"qFrom": 1, "qTo": 9, "price": 4.345454545}, {"qFrom": 10, "qTo": 29, "price": 4.345454545}, {"qFrom": 30, "qTo": 199, "price": 4.345454545}, {"qFrom": 200, "qTo": 499, "price": 1.681818182}, {"qFrom": 500, "qTo": 999, "price": 1.622727273}, {"qFrom": 1000, "qTo": null, "price": 1.593939394}], null, "https://lcsc.com/product-detail/Pre-ordered-transistors_ON-Semiconductor-RURG3060CC-F085_C606164.html", {"Basic/Extended": {"format": "${default}", "primary": "default", "values": {"default": ["Extended", "string"]}}, "Package": {"format": "${default}", "primary": "default", "values": {"default": ["TO-247-3", "string"]}}, "Status": {"format": "${default}", "primary": "default", "values": {"default": ["Active", "string"]}}}], ["C606158", "NVHL040N120SC1", 3, "ON Semiconductor", "Pre-ordered transistors RoHS", "", [{"qFrom": 1, "qTo": 9, "price": 27.159090909}, {"qFrom": 10, "qTo": 29, "price": 27.159090909}, {"qFrom": 30, "qTo": 199, "price": 27.159090909}, {"qFrom": 200, "qTo": 499, "price": 10.510606061}, {"qFrom": 500, "qTo": 999, "price": 10.140909091}, {"qFrom": 1000, "qTo": null, "price": 9.959090909}], null, "https://lcsc.com/product-detail/Pre-ordered-transistors_ON-Semiconductor-NVHL040N120SC1_C606158.html", {"Basic/Extended": {"format": "${default}", "primary": "default", "values": {"default": ["Extended", "string"]}}, "Package": {"format": "${default}", "primary": "default", "values": {"default": ["TO-247-3", "string"]}}, "Status": {"format": "${default}", "primary": "default", "values": {"default": ["Active", "string"]}}}], ["C606159", "NVHL110N65S3F", 3, "ON Semiconductor", "TO-247-3 Pre-ordered transistors RoHS", "", [{"qFrom": 1, "qTo": 9, "price": 6.807575758}, {"qFrom": 10, "qTo": 29, "price": 6.807575758}, {"qFrom": 30, "qTo": 199, "price": 6.807575758}, {"qFrom": 200, "qTo": 499, "price": 2.634848485}, {"qFrom": 500, "qTo": 999, "price": 2.542424242}, {"qFrom": 1000, "qTo": null, "price": 2.496969697}], null, "https://lcsc.com/product-detail/Pre-ordered-transistors_ON-Semiconductor-NVHL110N65S3F_C606159.html", {"Basic/Extended": {"format": "${default}", "primary": "default", "values": {"default": ["Extended", "string"]}}, "Package": {"format": "${default}", "primary": "default", "values": {"default": ["TO-247-3", "string"]}}, "Status": {"format": "${default}", "primary": "default", "values": {"default": ["Active", "string"]}}}], ["C538532", "MA12070", 64, "Infineon Technologies", "PG-VQFN-64 Pre-ordered transistors RoHS", "", [{"qFrom": 1, "qTo": 9, "price": 8.907575758}, {"qFrom": 10, "qTo": 29, "price": 8.907575758}, {"qFrom": 30, "qTo": 199, "price": 8.907575758}, {"qFrom": 200, "qTo": 499, "price": 3.446969697}, {"qFrom": 500, "qTo": 999, "price": 3.325757576}, {"qFrom": 1000, "qTo": null, "price": 3.266666667}], null, "https://lcsc.com/product-detail/Pre-ordered-transistors_Infineon-Technologies-MA12070_C538532.html", {"Basic/Extended": {"format": "${default}", "primary": "default", "values": {"default": ["Extended", "string"]}}, "Package": {"format": "${default}", "primary": "default", "values": {"default": ["PG-VQFN-64", "string"]}}, "Status": {"format": "${default}", "primary": "default", "values": {"default": ["Active", "string"]}}}], ["C510338", "RB521SM-60FHT2R", 2, "ROHM Semicon", "Pre-ordered transistors RoHS", "", [{"qFrom": 1, "qTo": 9, "price": 0.073333333}, {"qFrom": 10, "qTo": 29, "price": 0.073333333}, {"qFrom": 30, "qTo": 199, "price": 0.073333333}, {"qFrom": 200, "qTo": 499, "price": 0.028333333}, {"qFrom": 500, "qTo": 999, "price": 0.027424242}, {"qFrom": 1000, "qTo": null, "price": 0.026818182}], null, "https://lcsc.com/product-detail/Pre-ordered-transistors_ROHM-Semicon-RB521SM-60FHT2R_C510338.html", {"Basic/Extended": {"format": "${default}", "primary": "default", "values": {"default": ["Extended", "string"]}}, "Package": {"format": "${default}", "primary": "default", "values": {"default": ["SOD-52", "string"]}}, "Status": {"format": "${default}", "primary": "default", "values": {"default": ["Active", "string"]}}}], ["C510339", "RB521SM-60T2R", 2, "ROHM Semicon", "Pre-ordered transistors RoHS", "", [{"qFrom": 10, "qTo": 90, "price": 0.031818182}, {"qFrom": 100, "qTo": 290, "price": 0.023636364}, {"qFrom": 300, "qTo": 990, "price": 0.022121212}, {"qFrom": 1000, "qTo": 4990, "price": 0.020606061}, {"qFrom": 5000, "qTo": 9990, "price": 0.019848485}, {"qFrom": 10000, "qTo": null, "price": 0.019545455}], null, "https://lcsc.com/product-detail/Pre-ordered-transistors_ROHM-Semicon-RB521SM-60T2R_C510339.html", {"Basic/Extended": {"format": "${default}", "primary": "default", "values": {"default": ["Extended", "string"]}}, "Package": {"format": "${default}", "primary": "default", "values": {"default": ["SOD-52", "string"]}}, "Status": {"format": "${default}", "primary": "default", "values": {"default": ["Active", "string"]}}}], ["C603955", "NCV51460SN33T1G", 3, "ON Semiconductor", "8-SOIC Pre-ordered transistors RoHS", "", [{"qFrom": 1, "qTo": 9, "price": 1.190909091}, {"qFrom": 10, "qTo": 29, "price": 1.190909091}, {"qFrom": 30, "qTo": 199, "price": 1.190909091}, {"qFrom": 200, "qTo": 499, "price": 0.462121212}, {"qFrom": 500, "qTo": 999, "price": 0.445454545}, {"qFrom": 1000, "qTo": null, "price": 0.437878788}], null, "https://lcsc.com/product-detail/Pre-ordered-transistors_ON-Semiconductor-NCV51460SN33T1G_C603955.html", {"Basic/Extended": {"format": "${default}", "primary": "default", "values": {"default": ["Extended", "string"]}}, "Package": {"format": "${default}", "primary": "default", "values": {"default": ["8-SOIC", "string"]}}, "Status": {"format": "${default}", "primary": "default", "values": {"default": ["Active", "string"]}}}], ["C538881", "SAK-TC397XP-256F300S BD", 292, "Infineon Technologies", "PG-LFBGA-292 Pre-ordered transistors RoHS", "", [{"qFrom": 1, "qTo": 9, "price": 110.639393939}, {"qFrom": 10, "qTo": 29, "price": 110.639393939}, {"qFrom": 30, "qTo": 199, "price": 110.639393939}, {"qFrom": 200, "qTo": 499, "price": 42.816666667}, {"qFrom": 500, "qTo": 999, "price": 41.312121212}, {"qFrom": 1000, "qTo": null, "price": 40.568181818}], null, "https://lcsc.com/product-detail/Pre-ordered-transistors_Infineon-Technologies-SAK-TC397XP-256F300S-BD_C538881.html", {"Basic/Extended": {"format": "${default}", "primary": "default", "values": {"default": ["Extended", "string"]}}, "Package": {"format": "${default}", "primary": "default", "values": {"default": ["PG-LFBGA-292", "string"]}}, "Status": {"format": "${default}", "primary": "default", "values": {"default": ["Active", "string"]}}}], ["C917489", "VCUT0505B-HD1-GS08", 2, "Vishay Intertech", "LLP1006-2 Pre-ordered transistors RoHS", "", [{"qFrom": 1, "qTo": 9, "price": 0.130757576}, {"qFrom": 10, "qTo": 29, "price": 0.130757576}, {"qFrom": 30, "qTo": 199, "price": 0.130757576}, {"qFrom": 200, "qTo": 499, "price": 0.050606061}, {"qFrom": 500, "qTo": 999, "price": 0.048787879}, {"qFrom": 1000, "qTo": null, "price": 0.047878788}], null, "https://lcsc.com/product-detail/Pre-ordered-transistors_Vishay-Intertech-VCUT0505B-HD1-GS08_C917489.html", {"Basic/Extended": {"format": "${default}", "primary": "default", "values": {"default": ["Extended", "string"]}}, "Package": {"format": "${default}", "primary": "default", "values": {"default": ["LLP1006-2", "string"]}}, "Status": {"format": "${default}", "primary": "default", "values": {"default": ["Active", "string"]}}}], ["C538817", "SAK-TC277TP-64F200S DC", 292, "Infineon Technologies", "PG-LFBGA-292 Pre-ordered transistors RoHS", "", [{"qFrom": 1, "qTo": 999, "price": 0.000606061}, {"qFrom": 1000, "qTo": null, "price": 0.000151515}], null, "https://lcsc.com/product-detail/Pre-ordered-transistors_Infineon-Technologies-SAK-TC277TP-64F200S-DC_C538817.html", {"Basic/Extended": {"format": "${default}", "primary": "default", "values": {"default": ["Extended", "string"]}}, "Package": {"format": "${default}", "primary": "default", "values": {"default": ["PG-LFBGA-292", "string"]}}, "Status": {"format": "${default}", "primary": "default", "values": {"default": ["Active", "string"]}}}], ["C603929", "NCV4274CST50T3G", 4, "ON Semiconductor", "TO-252-5 Pre-ordered transistors RoHS", "", [{"qFrom": 1, "qTo": 999, "price": 0.000606061}, {"qFrom": 1000, "qTo": null, "price": 0.000151515}], null, "https://lcsc.com/product-detail/Linear-Voltage-Regulators-LDO_ON-Semiconductor-NCV4274CST50T3G_C603929.html", {"Output Configuration": {"format": "${default}", "primary": "default", "values": {"default": ["-", "string"]}}, "Output Type": {"format": "${default}", "primary": "default", "values": {"default": ["-", "string"]}}, "Number of Output Channels": {"format": "${default}", "primary": "default", "values": {"default": ["-", "string"]}}, "Enabling feet": {"format": "${default}", "primary": "default", "values": {"default": ["-", "string"]}}, "Voltage - Input (Max)": {"format": "${voltage}", "primary": "voltage", "values": {"voltage": ["NaN", "voltage"]}}, "Voltage - Output (Fixed)": {"format": "${voltage}", "primary": "voltage", "values": {"voltage": ["NaN", "voltage"]}}, "Voltage - Output (adj)": {"format": "${default}", "primary": "default", "values": {"default": ["-", "string"]}}, "Voltage Dropout (Max)": {"format": "${default}", "primary": "default", "values": {"default": ["-", "string"]}}, "Output Current (Max)": {"format": "${current}", "primary": "current", "values": {"current": ["NaN", "current"]}}, "Quiescent Current (Iq)": {"format": "${default}", "primary": "default", "values": {"default": ["-", "string"]}}, "Current - Supply (Max)": {"format": "${current}", "primary": "current", "values": {"current": ["NaN", "current"]}}, "Ripple Rejection (PSRR)": {"format": "${default}", "primary": "default", "values": {"default": ["-", "string"]}}, "Operating Temperature": {"format": "${default}", "primary": "default", "values": {"default": ["-", "string"]}}, "Basic/Extended": {"format": "${default}", "primary": "default", "values": {"default": ["Extended", "string"]}}, "Package": {"format": "${default}", "primary": "default", "values": {"default": ["TO-252-5", "string"]}}, "Status": {"format": "${default}", "primary": "default", "values": {"default": ["Active", "string"]}}}], ["C606120", "FFSD10120A", 3, "ON Semiconductor", "D-PAK-3 Pre-ordered transistors RoHS", "", [{"qFrom": 1, "qTo": 999, "price": 0.000606061}, {"qFrom": 1000, "qTo": null, "price": 0.000151515}], null, "https://lcsc.com/product-detail/Pre-ordered-transistors_ON-Semiconductor-FFSD10120A_C606120.html", {"Basic/Extended": {"format": "${default}", "primary": "default", "values": {"default": ["Extended", "string"]}}, "Package": {"format": "${default}", "primary": "default", "values": {"default": ["D-PAK-3", "string"]}}, "Status": {"format": "${default}", "primary": "default", "values": {"default": ["Active", "string"]}}}], ["C538808", "SAK-TC275TP-64F200N DC", 177, "Infineon Technologies", "PG-LQFP-176 Pre-ordered transistors RoHS", "", [{"qFrom": 1, "qTo": 9, "price": 49.134848485}, {"qFrom": 10, "qTo": 29, "price": 49.134848485}, {"qFrom": 30, "qTo": 199, "price": 49.134848485}, {"qFrom": 200, "qTo": 499, "price": 19.015151515}, {"qFrom": 500, "qTo": 999, "price": 18.346969697}, {"qFrom": 1000, "qTo": null, "price": 18.016666667}], null, "https://lcsc.com/product-detail/Pre-ordered-transistors_Infineon-Technologies-SAK-TC275TP-64F200N-DC_C538808.html", {"Basic/Extended": {"format": "${default}", "primary": "default", "values": {"default": ["Extended", "string"]}}, "Package": {"format": "${default}", "primary": "default", "values": {"default": ["PG-LQFP-176", "string"]}}, "Status": {"format": "${default}", "primary": "default", "values": {"default": ["Active", "string"]}}}]], "category": "Transistors", "subcategory": "Pre-ordered transistors"}